llama_index/postprocessor/mixedbreadai_rerank/__init__.py
llama_index/postprocessor/mixedbreadai_rerank/base.py
llama_index_postprocessor_mixedbreadai_rerank-0.5.1.dist-info/METADATA
llama_index_postprocessor_mixedbreadai_rerank-0.5.1.dist-info/WHEEL
llama_index_postprocessor_mixedbreadai_rerank-0.5.1.dist-info/licenses/LICENSE
llama_index_postprocessor_mixedbreadai_rerank-0.5.1.dist-info/RECORD
